medvqa/__init__.py
medvqa/cli.py
medvqa/competitions/__init__.py
medvqa/competitions/gi-2025/__init__.py
medvqa/competitions/gi-2025/submission_portal.py
medvqa/competitions/gi-2025/task_1.py
medvqa/competitions/gi-2025/task_2.py
medvqa/competitions/medico-2025/__init__.py
medvqa/competitions/medico-2025/submission_portal.py
medvqa/competitions/medico-2025/task_1.py
medvqa/competitions/medico-2025/task_2.py
medvqa/submission_samples/gi-2025/submission_task1.py
medvqa/submission_samples/gi-2025/submission_task2.py
medvqa/submission_samples/medico-2025/submission_task1.py
medvqa/submission_samples/medico-2025/submission_task1_swift.py
medvqa/submission_samples/medico-2025/submission_task2.py
medvqa-0.15.3.dist-info/METADATA
medvqa-0.15.3.dist-info/WHEEL
medvqa-0.15.3.dist-info/entry_points.txt
medvqa-0.15.3.dist-info/top_level.txt
medvqa-0.15.3.dist-info/RECORD
