Metadata-Version: 2.4
Name: medvqa
Version: 0.15.3
Summary: Competition Submission CLI for ImageCLEFmed-MedVQA-GI-2025 (https://github.com/simula/ImageCLEFmed-MEDVQA-GI-2025)
Author-email: Sushant Gautam <sushant@simula.no>
License: MIT
Project-URL: Homepage, https://github.com/SushantGautam/MedVQA
Project-URL: Issues, https://github.com/SushantGautam/MedVQA/issues
Classifier: Programming Language :: Python :: 3
Classifier: Operating System :: OS Independent
Requires-Python: >=3.6
Requires-Dist: huggingface_hub
Requires-Dist: huggingface_hub[hf_transfer]
Requires-Dist: gradio_client>=1.8.0
